MF_Tools/VT_sliders.py
MF_Tools/__init__.py
MF_Tools/animations.py
MF_Tools/debug.py
MF_Tools/dual_compatibility.py
MF_Tools/geometry.py
MF_Tools/misc.py
MF_Tools/rescaling.py
MF_Tools/transforms.py
MF_Tools/updaters.py
mf_tools-1.4.3.dist-info/LICENSE
mf_tools-1.4.3.dist-info/METADATA
mf_tools-1.4.3.dist-info/WHEEL
mf_tools-1.4.3.dist-info/entry_points.txt
mf_tools-1.4.3.dist-info/RECORD
