Metadata-Version: 2.3
Name: MF-Tools
Version: 1.4.3
Summary: Collection of helpful utilities for Manim
License: MIT
Author: John Connell
Author-email: johnconnelltutor@gmail.com
Requires-Python: >=3.8
Classifier: License :: OSI Approved :: MIT License
Classifier: Programming Language :: Python :: 3
Classifier: Programming Language :: Python :: 3.8
Classifier: Programming Language :: Python :: 3.9
Classifier: Programming Language :: Python :: 3.10
Classifier: Programming Language :: Python :: 3.11
Classifier: Programming Language :: Python :: 3.12
Classifier: Programming Language :: Python :: 3.13
Provides-Extra: manimce
Provides-Extra: manimgl
Requires-Dist: manim (>=0.17.0) ; extra == "manimce"
Requires-Dist: manimgl (>=1.7.0) ; extra == "manimgl"
Project-URL: Repository, https://github.com/TheMathematicFanatic/MF_Tools
